MANIFEST.in
README.rst
scrapy_boilerplate.py
setup.py
scrapy_boilerplate.egg-info/PKG-INFO
scrapy_boilerplate.egg-info/SOURCES.txt
scrapy_boilerplate.egg-info/dependency_links.txt
scrapy_boilerplate.egg-info/requires.txt
scrapy_boilerplate.egg-info/top_level.txt