Metadata-Version: 1.1
Name: scrapy-boilerplate
Version: 0.2.1
Summary: Small set of utilities to simplify writing Scrapy spiders.
Home-page: https://github.com/darkrho/scrapy-boilerplate
Author: Rolando Espinoza La fuente
Author-email: darkrho@gmail.com
License: BSD
Platform: UNKNOWN
Classifier: Programming Language :: Python
Classifier: Development Status :: 4 - Beta
Classifier: Intended Audience :: Developers
